cmply/__init__.py
docker_runner/__init__.py
cmply-0.1.8.dist-info/entry_points.txt
cmply-0.1.8.dist-info/LICENSE.txt
cmply-0.1.8.dist-info/WHEEL
cmply-0.1.8.dist-info/METADATA
cmply-0.1.8.dist-info/RECORD
